[
  {"question": "ما هو اسم بطل أنمي Naruto؟", "response": "ناروتو أوزوماكي"},
  {"question": "من هو قائد فريق 7 في أنمي Naruto؟", "response": "كاكاشي هاتاكي"},
  {"question": "ما هو اسم شيطان الثعلب في Naruto؟", "response": "كوراما"},
  {"question": "من قتل عشيرة أوتشيها في Naruto؟", "response": "إيتاشي أوتشيها"},
  {"question": "ما هو اسم بطل أنمي One Piece؟", "response": "مونكي دي لوفي"},
  {"question": "ما هو حلم لوفي في One Piece؟", "response": "أن يصبح ملك القراصنة"},
  {"question": "من هو صانع سيف زورو الأخضر في One Piece؟", "response": "كوزابورو واجورو"},
  {"question": "ما اسم سفينة طاقم قبعة القش في One Piece؟", "response": "ثاوزند سني"},
  {"question": "من هو بطل أنمي Dragon Ball؟", "response": "سون غوكو"},
  {"question": "ما هو اسم ابن غوكو الأكبر في Dragon Ball؟", "response": "غوهان"},
  {"question": "من هو غريم غوكو الأبرز في Dragon Ball Z؟", "response": "فيغيتا"},
  {"question": "ما هو اسم التحول الأسطوري في Dragon Ball؟", "response": "سوبر سايان"},
  {"question": "ما اسم بطل أنمي Bleach؟", "response": "إيتشيغو كوروساكي"},
  {"question": "ما هو اسم سيف إيتشيغو في Bleach؟", "response": "زانغيتسو"},
  {"question": "من هو الشرير الرئيسي في Bleach؟", "response": "أيزن سوسكي"},
  {"question": "ما اسم بطل أنمي Attack on Titan؟", "response": "إيرين ييغر"},
  {"question": "ما هو اسم الجدار الأول في Attack on Titan؟", "response": "الجدار ماريا"},
  {"question": "من هو صاحب تيتان المدرع في Attack on Titan؟", "response": "ريينر براون"},
  {"question": "ما اسم بطل أنمي My Hero Academia؟", "response": "إيزوكو ميدوريا"},
  {"question": "ما هو اسم قوة ميدوريا في My Hero Academia؟", "response": "ون فور أول"},
  {"question": "من هو معلم ميدوريا في My Hero Academia؟", "response": "أول مايت"},
  {"question": "ما اسم المدرسة في My Hero Academia؟", "response": "UA"},
  {"question": "ما اسم بطل أنمي Demon Slayer؟", "response": "تانجيرو كاميادو"},
  {"question": "من حول أخت تانجيرو إلى شيطان في Demon Slayer؟", "response": "موزان كيبوتسوجي"},
  {"question": "ما اسم أخت تانجيرو في Demon Slayer؟", "response": "نيزوكو"},
  {"question": "ما هو أسلوب تانجيرو القتالي في Demon Slayer؟", "response": "تنفس الماء"},
  {"question": "ما اسم بطل أنمي Hunter x Hunter؟", "response": "غون فريكس"},
  {"question": "ما اسم صديق غون الأفضل في Hunter x Hunter؟", "response": "كيلوا زولديك"},
  {"question": "ما هو اسم الامتحان الرئيسي في Hunter x Hunter؟", "response": "امتحان الهانتر"},
  {"question": "ما اسم بطل أنمي Fullmetal Alchemist؟", "response": "إدوارد إلريك"},
  {"question": "ما الذي فقده إدوارد في FMA؟", "response": "ذراعه اليسرى وساقه اليمنى"},
  {"question": "ما اسم أخ إدوارد في FMA؟", "response": "ألفونس إلريك"},
  {"question": "ما هو الحجر الفلسفي في FMA؟", "response": "حجر الفيلسوف"},
  {"question": "ما اسم بطل أنمي Death Note؟", "response": "لايت ياغامي"},
  {"question": "ما اسم المحقق الذي يطارد لايت في Death Note؟", "response": "L"},
  {"question": "ما اسم الشيطان في Death Note؟", "response": "ريوك"},
  {"question": "ما اسم بطل أنمي Sword Art Online؟", "response": "كيريتو"},
  {"question": "ما اسم حبيبة كيريتو في SAO؟", "response": "أسونا"},
  {"question": "ما اسم بطل أنمي Tokyo Ghoul؟", "response": "كان كاناكي"},
  {"question": "ما اسم المنظمة التي تطارد الغولات في Tokyo Ghoul؟", "response": "CCG"},
  {"question": "ما اسم بطل أنمي Re:Zero؟", "response": "سوباهارو ناتسوكي"},
  {"question": "ما هي قدرة سوباهارو في Re:Zero؟", "response": "العودة بالموت"},
  {"question": "ما اسم بطلة أنمي Violet Evergarden؟", "response": "فيوليت إيفرغاردن"},
  {"question": "ما اسم بطل أنمي Code Geass؟", "response": "ليلوش لامبيروج"},
  {"question": "ما اسم قدرة ليلوش في Code Geass؟", "response": "Geass"},
  {"question": "ما اسم بطل أنمي Fairy Tail؟", "response": "ناتسو دراغنيل"},
  {"question": "ما نوع السحر الذي يستخدمه ناتسو في Fairy Tail؟", "response": "سحر النار"},
  {"question": "ما اسم الجيلد في Fairy Tail؟", "response": "فيري تيل"},
  {"question": "ما اسم بطل أنمي Black Clover؟", "response": "آستا"},
  {"question": "ما اسم الكتاب السحري لآستا في Black Clover؟", "response": "كتاب الأربع أوراق"},
  {"question": "ما اسم بطل أنمي One Punch Man؟", "response": "سايتاما"},
  {"question": "كم عدد التدريبات اليومية لسايتاما في OPM؟", "response": "100 ضغطة و100 جلسة و100 قرفصاء و10 كيلومتر"},
  {"question": "ما اسم بطل أنمي Mob Psycho 100؟", "response": "شيغيو كاغياما"},
  {"question": "ما اسم بطل أنمي Haikyuu؟", "response": "شويو هيناتا"},
  {"question": "ما اسم الفريق في Haikyuu؟", "response": "كاراسونو"},
  {"question": "ما اسم بطل أنمي Blue Lock؟", "response": "يوئيتشي إيساغي"},
  {"question": "ما هو هدف Blue Lock؟", "response": "إيجاد أفضل مهاجم في العالم"},
  {"question": "ما اسم بطل أنمي Jujutsu Kaisen؟", "response": "يوجي إيتادوري"},
  {"question": "من يسكن في جسد إيتادوري في JJK؟", "response": "ريوميين سوكونا"},
  {"question": "ما اسم معلم إيتادوري في JJK؟", "response": "ساتورو غوجو"},
  {"question": "ما اسم أنمي الشياطين والصيادين لـ Tanjiro؟", "response": "Demon Slayer"},
  {"question": "ما اسم بطل أنمي Vinland Saga؟", "response": "ثورفين"},
  {"question": "ما اسم بطل أنمي Berserk؟", "response": "غاتس"},
  {"question": "ما اسم السيف الضخم في Berserk؟", "response": "سيف العلامة"},
  {"question": "ما اسم بطل أنمي Cowboy Bebop؟", "response": "سبايك سبيغل"},
  {"question": "ما اسم المركبة الفضائية في Cowboy Bebop؟", "response": "Bebop"},
  {"question": "ما اسم بطل أنمي Trigun؟", "response": "فاش ذا ستامبيد"},
  {"question": "ما اسم بطل أنمي Evangelion؟", "response": "شينجي إيكاري"},
  {"question": "ما اسم المنظمة في Evangelion؟", "response": "NERV"},
  {"question": "ما اسم بطل أنمي Steins;Gate؟", "response": "رينتارو أوكابي"},
  {"question": "ما الجهاز الذي اخترعه أوكابي في Steins;Gate؟", "response": "هاتف الميكروويف"},
  {"question": "ما اسم بطل أنمي No Game No Life؟", "response": "شيرو وسورا"},
  {"question": "ما هو شعار No Game No Life؟", "response": "الألعاب"},
  {"question": "ما اسم بطل أنمي Overlord؟", "response": "أينز أول غاون"},
  {"question": "ما اسم مملكة أينز في Overlord؟", "response": "نازاريك"},
  {"question": "ما اسم بطل أنمي Sword Art Online Alicization؟", "response": "يوجين كيريغايا"},
  {"question": "ما اسم بطل أنمي That Time I Got Reincarnated as a Slime؟", "response": "ريموروتيمبيست"},
  {"question": "ما اسم التنين في Slime؟", "response": "فيلدورا"},
  {"question": "ما اسم بطل أنمي Konosuba؟", "response": "كازوما ساتو"},
  {"question": "ما اسم الإلهة في Konosuba؟", "response": "أكوا"},
  {"question": "ما اسم بطل أنمي Log Horizon؟", "response": "شيرو"},
  {"question": "ما اسم بطل أنمي Danmachi؟", "response": "بيل كرانيل"},
  {"question": "ما اسم الإلهة في Danmachi؟", "response": "هيستيا"},
  {"question": "ما اسم بطل أنمي Goblin Slayer؟", "response": "قاتل الغوبلن"},
  {"question": "ما اسم بطل أنمي Made in Abyss؟", "response": "ريكو"},
  {"question": "ما اسم الروبوت في Made in Abyss؟", "response": "ريغ"},
  {"question": "ما اسم بطل أنمي Dr. Stone؟", "response": "سينكو إيشيغامي"},
  {"question": "ما هو المعدن الذي يذوب الحجر في Dr. Stone؟", "response": "نيترو"},
  {"question": "ما اسم بطل أنمي The Promised Neverland؟", "response": "إيما"},
  {"question": "ما اسم الملجأ في The Promised Neverland؟", "response": "Grace Field"},
  {"question": "ما اسم بطل أنمي Dororo؟", "response": "هيياكيماروا"},
  {"question": "ما اسم بطل أنمي Inuyasha؟", "response": "إينوياشا"},
  {"question": "ما اسم الفتاة في Inuyasha؟", "response": "كاغومي هيغوراشي"},
  {"question": "ما اسم بطل أنمي Rurouni Kenshin؟", "response": "كينشين هيمورا"},
  {"question": "ما لقب كينشين في Rurouni Kenshin؟", "response": "قاتل الباتوساي"},
  {"question": "ما اسم بطل أنمي Samurai Champloo؟", "response": "موغن وجين"},
  {"question": "ما اسم بطل أنمي Ghost in the Shell؟", "response": "الميجور موتوكو كوسانانغي"},
  {"question": "ما اسم بطل أنمي Akira؟", "response": "شوتارو كانيدا"},
  {"question": "ما اسم بطل أنمي Your Lie in April؟", "response": "كوسيي أريما"},
  {"question": "ما اسم الفتاة في Your Lie in April؟", "response": "كاوري ميازونو"},
  {"question": "ما اسم بطل أنمي A Silent Voice؟", "response": "شويا إيشيدا"},
  {"question": "ما اسم الفتاة في A Silent Voice؟", "response": "شوكو نيشيميا"},
  {"question": "ما اسم بطل أنمي Anohana؟", "response": "جينتا مياظومي"},
  {"question": "ما اسم الروح في Anohana؟", "response": "مينما"},
  {"question": "ما اسم بطل أنمي Clannad؟", "response": "توموياأوكازاكي"},
  {"question": "ما اسم حبيبة توموياأوكازاكي في Clannad؟", "response": "ناغيسا فوروكاوا"},
  {"question": "ما اسم بطل أنمي Angel Beats؟", "response": "يوزورو أوتوناشي"},
  {"question": "ما اسم بطل أنمي Charlotte؟", "response": "يو أوتوساكا"},
  {"question": "ما اسم بطل أنمي Plastic Memories؟", "response": "تسوكاسا ميزوغاكي"},
  {"question": "ما اسم بطل أنمي Tokyo Revengers؟", "response": "تاكيمتشي هانانكي"},
  {"question": "ما اسم العصابة في Tokyo Revengers؟", "response": "طاقم طوكيو مانجي"},
  {"question": "ما اسم بطل أنمي Chainsaw Man؟", "response": "ديانجي"},
  {"question": "ما اسم الشيطانة في Chainsaw Man؟", "response": "باور"},
  {"question": "ما اسم بطل أنمي Spy x Family؟", "response": "لويد فورغر"},
  {"question": "ما اسم الطفلة في Spy x Family؟", "response": "أنيا فورغر"},
  {"question": "ما هي قدرة أنيا في Spy x Family؟", "response": "قراءة الأفكار"},
  {"question": "ما اسم بطل أنمي Mushoku Tensei؟", "response": "رودوس غريرات"},
  {"question": "ما اسم بطل أنمي Shield Hero؟", "response": "ناوفومي إيواتاني"},
  {"question": "ما اسم الراكون في Shield Hero؟", "response": "رافتاليا"},
  {"question": "ما اسم بطل أنمي Rising of the Shield Hero؟", "response": "ناوفومي إيواتاني"},
  {"question": "ما اسم بطل أنمي Isekai Quartet؟", "response": "شخصيات متعددة"},
  {"question": "ما اسم بطل أنمي Sword Art Online Progressive؟", "response": "أسونا يوكي"},
  {"question": "ما اسم بطل أنمي Kakegurui؟", "response": "يوميكو جابامي"},
  {"question": "ما اسم المدرسة في Kakegurui؟", "response": "مدرسة هياكاو"},
  {"question": "ما اسم بطل أنمي Classroom of the Elite؟", "response": "كيويتاكا أيانوكوجي"},
  {"question": "ما اسم بطل أنمي The Disastrous Life of Saiki K؟", "response": "كوسكو سايكي"},
  {"question": "ما هي قدرة سايكي؟", "response": "القدرات الخارقة"},
  {"question": "ما اسم بطل أنمي Gintama؟", "response": "غينتوكي ساكاتا"},
  {"question": "ما اسم بطل أنمي Toriko؟", "response": "توريكو"},
  {"question": "ما اسم بطل أنمي Katekyo Hitman Reborn؟", "response": "تسونا ساواداا"},
  {"question": "ما اسم المدرب في Hitman Reborn؟", "response": "ريبورن"},
  {"question": "ما اسم بطل أنمي Beelzebub؟", "response": "تاتسومي أوغا"},
  {"question": "ما اسم الشيطان الرضيع في Beelzebub؟", "response": "بيبي"},
  {"question": "ما اسم بطل أنمي Medaka Box؟", "response": "ميداكا كوروكامي"},
  {"question": "ما اسم بطل أنمي Kuroko no Basket؟", "response": "تيتسويا كوروكو"},
  {"question": "ما اسم الفريق في Kuroko no Basket؟", "response": "سيرين"},
  {"question": "ما اسم بطل أنمي Slam Dunk؟", "response": "هاناميتشي ساكوراغي"},
  {"question": "ما اسم الفريق في Slam Dunk؟", "response": "شوهوكو"},
  {"question": "ما اسم بطل أنمي Inazuma Eleven؟", "response": "ماركو رييتو"},
  {"question": "ما اسم بطل أنمي Captain Tsubasa؟", "response": "توسيرو تسوباسا"},
  {"question": "ما اسم بطل أنمي Hajime no Ippo؟", "response": "إيبو ماكونوتشي"},
  {"question": "ما اسم بطل أنمي Ashita no Joe؟", "response": "جو ياباكي"},
  {"question": "ما اسم بطل أنمي Yowamushi Pedal؟", "response": "ساكامتشي أونودا"},
  {"question": "ما اسم بطل أنمي Free؟", "response": "هارتكا ناناسي"},
  {"question": "ما اسم بطل أنمي Ping Pong the Animation؟", "response": "ماكوتو تسوكيموتو"},
  {"question": "ما اسم بطل أنمي Kimetsu no Yaiba Movie؟", "response": "تانجيرو كاميادو"},
  {"question": "ما اسم الفيلم الأول لـ Demon Slayer؟", "response": "قطار موغن"},
  {"question": "من مات في فيلم Demon Slayer؟", "response": "رينغوكو"},
  {"question": "ما اسم بطل أنمي Spirited Away؟", "response": "تشيهيرو"},
  {"question": "ما اسم الحمام في Spirited Away؟", "response": "يوبابا"},
  {"question": "ما اسم بطل أنمي Princess Mononoke؟", "response": "أشيتاكا"},
  {"question": "من أنتج Spirited Away؟", "response": "استوديو غيبلي"},
  {"question": "ما اسم بطل أنمي Howl's Moving Castle؟", "response": "هاول"},
  {"question": "ما اسم بطل أنمي Nausicaa؟", "response": "ناوسيكا"},
  {"question": "ما اسم بطل أنمي Castle in the Sky؟", "response": "شيتا وباز"},
  {"question": "ما اسم بطل أنمي My Neighbor Totoro؟", "response": "ساتسوكي وميي"},
  {"question": "ما اسم المخلوق الغابوي في My Neighbor Totoro؟", "response": "توتورو"},
  {"question": "ما اسم مخرج أنمي غيبلي الشهير؟", "response": "هايو ميازاكي"},
  {"question": "ما اسم بطل أنمي Grave of the Fireflies؟", "response": "سيتا"},
  {"question": "ما اسم بطل أنمي Wolf Children؟", "response": "هانا"},
  {"question": "ما اسم بطل أنمي Summer Wars؟", "response": "كينتا أويدا"},
  {"question": "ما اسم بطل فيلم Your Name؟", "response": "تاكي وميتسوها"},
  {"question": "من أخرج فيلم Your Name؟", "response": "ماكوتو شينكاي"},
  {"question": "ما اسم بطل فيلم Weathering with You؟", "response": "هودوكا موريشيما"},
  {"question": "ما اسم بطل أنمي Sword of the Stranger؟", "response": "كوتارو"},
  {"question": "ما اسم بطل أنمي Planetes؟", "response": "هاشيما هوشينو"},
  {"question": "ما اسم بطل أنمي Terra e؟", "response": "جومي ماتسورا"},
  {"question": "ما اسم بطل أنمي Eureka Seven؟", "response": "رينتون تيرستون"},
  {"question": "ما اسم بطل أنمي RahXephon؟", "response": "آياتو كاميناا"},
  {"question": "ما اسم بطل أنمي Escaflowne؟", "response": "هيتومي كانظاكي"},
  {"question": "ما اسم بطل أنمي Macross؟", "response": "هيكارو إيتشيجو"},
  {"question": "ما اسم بطل أنمي Space Battleship Yamato؟", "response": "سوسيمو كودو"},
  {"question": "ما هو اسم عالم أنمي Sword Art Online؟", "response": "أينكراد"},
  {"question": "كم عدد طوابق أينكراد في SAO؟", "response": "100 طابق"},
  {"question": "ما اسم بطل أنمي Accel World؟", "response": "هاروتيكو أريتا"},
  {"question": "ما اسم بطل أنمي Danganronpa؟", "response": "ماكوتو ناييغي"},
  {"question": "ما اسم الدب في Danganronpa؟", "response": "مونوكوما"},
  {"question": "ما اسم بطل أنمي Future Diary؟", "response": "يوكيتيرو أمانو"},
  {"question": "ما اسم الشخصية المجنونة في Future Diary؟", "response": "يونو غاسي"},
  {"question": "ما اسم بطل أنمي Deadman Wonderland؟", "response": "غانتا إيغارياشي"},
  {"question": "ما اسم بطل أنمي Elfen Lied؟", "response": "لوسي"},
  {"question": "ما اسم بطل أنمي Higurashi؟", "response": "كيئيتشي ماييبارا"},
  {"question": "ما اسم بطل أنمي Umineko؟", "response": "باتيرا أوشيماء"},
  {"question": "ما اسم بطل أنمي Another؟", "response": "كوئيتشي ساكاكيبارا"},
  {"question": "ما اسم بطل أنمي Parasyte؟", "response": "شينإيتشي إيزومي"},
  {"question": "ما اسم الطفيل في Parasyte؟", "response": "ميغي"},
  {"question": "ما اسم بطل أنمي Ajin؟", "response": "كي ناغاي"},
  {"question": "ما اسم بطل أنمي Terra Formars؟", "response": "أكاري هيزامارو"},
  {"question": "ما اسم بطل أنمي Attack on Titan Season 4؟", "response": "إيرين ييغر"},
  {"question": "ما اسم التيتان الشبيه بالحرب في AOT؟", "response": "تيتان المطرقة"},
  {"question": "ما اسم بطل أنمي Kabaneri؟", "response": "إيكوما"},
  {"question": "ما اسم بطل أنمي God Eater؟", "response": "لينكا لي"},
  {"question": "ما اسم بطل أنمي Claymore؟", "response": "كلير"},
  {"question": "ما اسم بطل أنمي D.Gray-man؟", "response": "ألين ووكر"},
  {"question": "ما اسم القوة في D.Gray-man؟", "response": "إينوسنس"},
  {"question": "ما اسم بطل أنمي Blue Exorcist؟", "response": "ريكو أوكوميرا"},
  {"question": "من هو والد ريكو في Blue Exorcist؟", "response": "الشيطان الأزرق سيتان"},
  {"question": "ما اسم بطل أنمي Soul Eater؟", "response": "ماكا ألباهارن"},
  {"question": "ما اسم شريك ماكا في Soul Eater؟", "response": "سول إيتر إيفانس"},
  {"question": "ما اسم المدرسة في Soul Eater؟", "response": "DWMA"},
  {"question": "ما اسم بطل أنمي Magi؟", "response": "ألاهدين"},
  {"question": "ما اسم بطل أنمي Zatch Bell؟", "response": "كيو ماكامورا"},
  {"question": "ما اسم الشيطان في Zatch Bell؟", "response": "زاتش بيل"},
  {"question": "ما اسم بطل أنمي Yu Yu Hakusho؟", "response": "يوسكي أورامياشي"},
  {"question": "ما اسم بطل أنمي Yu-Gi-Oh؟", "response": "يوغي موتو"},
  {"question": "ما اسم شيطان يوغي في Yu-Gi-Oh؟", "response": "يامي"},
  {"question": "ما اسم بطل أنمي Beyblade؟", "response": "تايسون غرانغر"},
  {"question": "ما اسم بطل أنمي Digimon؟", "response": "تاي كامييا"},
  {"question": "ما اسم ديجيمون الأشهر؟", "response": "أغومون"},
  {"question": "ما اسم بطل أنمي Pokemon؟", "response": "آش كيتشوم"},
  {"question": "ما اسم أول بوكيمون لآش؟", "response": "بيكاتشو"},
  {"question": "ما اسم الرفيق الأول لآش في Pokemon؟", "response": "ميستي"},
  {"question": "من هو البطل الخفي في AOT؟", "response": "ليفاي أيكيرمان"},
  {"question": "ما اسم فيلق ليفاي في AOT؟", "response": "فيلق الاستطلاع"},
  {"question": "ما اسم بطل أنمي Vinland Saga الموسم 2؟", "response": "ثورفين"},
  {"question": "ما اسم شخصية الكومدي في Gintama؟", "response": "غينتوكي"},
  {"question": "ما لون شعر غينتوكي في Gintama؟", "response": "فضي"},
  {"question": "ما اسم بطل أنمي Bleach TYBW؟", "response": "إيتشيغو كوروساكي"},
  {"question": "ما اسم التحول النهائي لإيتشيغو في Bleach؟", "response": "True Bankai"},
  {"question": "ما اسم والد إيتشيغو في Bleach؟", "response": "إيسين كوروساكي"}
]
